LICENSE
MANIFEST.in
README
setup.py
leaner/__init__.py
leaner/admin.py
leaner/forms.py
leaner/middleware.py
leaner/models.py
leaner/signal.py
leaner/urls.py
leaner/utils.py
leaner/views.py
leaner.egg-info/PKG-INFO
leaner.egg-info/SOURCES.txt
leaner.egg-info/dependency_links.txt
leaner.egg-info/not-zip-safe
leaner.egg-info/requires.txt
leaner.egg-info/top_level.txt
leaner/goalrecord/__init__.py
leaner/goalrecord/base.py
leaner/goalrecord/dynamodb.py
leaner/goalrecord/rel_db.py
leaner/goalrecord/utils.py
leaner/static/leaner/css/bootstrap-responsive.css
leaner/static/leaner/css/bootstrap-responsive.min.css
leaner/static/leaner/css/bootstrap.css
leaner/static/leaner/css/bootstrap.min.css
leaner/static/leaner/css/leaner.css
leaner/static/leaner/img/glyphicons-halflings-white.png
leaner/static/leaner/img/glyphicons-halflings.png
leaner/static/leaner/js/bootstrap.js
leaner/static/leaner/js/bootstrap.min.js
leaner/templates/leaner/base.html
leaner/templates/leaner/switch-detail.html
leaner/templates/leaner/switch-report.html
leaner/templates/leaner/test-switch-page-goalrecord.html
leaner/templates/leaner/test-switch-page.html
leaner/templates/leaner/templatetags/goal_record_report.html
leaner/templatetags/__init__.py
leaner/templatetags/leaner_tags.py
leaner/tests/__init__.py
leaner/tests/middleware.py
leaner/tests/user_status.py
leaner/tests/views.py
leaner_rel_db/__init__.py
leaner_rel_db/models.py
leaner_rel_db/views.py