Metadata-Version: 1.1
Name: leaner
Version: 0.1.6.4
Summary: This project was inspired by "The Lean Startup" by Eric Ries "
Home-page: https://bitbucket.org/brianjinwright/leaner
Author: Brian Jinwright
Author-email: team@ipoots.com
License: Apache
Keywords: test,django,lean startup,web
Platform: UNKNOWN
Classifier: Programming Language :: Python
Classifier: Topic :: Software Development :: Libraries :: Python Modules
Classifier: Environment :: Web Environment
